{
  "generated_at": "2026-04-17 04:35 +0700",
  "repo": {
    "active_repo": "/Users/anton/Desktop/MagonOS-Standalone",
    "donor_repo": "/Users/anton/Desktop/MagonOS/MagonOS"
  },
  "validated_contour_en": [
    "company",
    "commercial/customer context",
    "opportunity",
    "quote intent / RFQ boundary",
    "production handoff",
    "production board"
  ],
  "validated_contour_ru": [
    "company",
    "commercial/customer context",
    "opportunity",
    "quote intent / RFQ boundary",
    "production handoff",
    "production board"
  ],
  "owned_capabilities_en": [
    "supplier intelligence pipeline",
    "normalization / enrichment / dedup / scoring",
    "review queue",
    "routing / qualification decisions",
    "feedback ledger / projection",
    "workforce estimation"
  ],
  "owned_capabilities_ru": [
    "supplier intelligence pipeline",
    "normalization / enrichment / dedup / scoring",
    "review queue",
    "routing / qualification decisions",
    "feedback ledger / projection",
    "workforce estimation"
  ],
  "danger_overlap_en": [
    "customer/account identity",
    "opportunity/lead ownership",
    "RFQ / quote boundary"
  ],
  "danger_overlap_ru": [
    "customer/account identity",
    "opportunity/lead ownership",
    "RFQ / quote boundary"
  ],
  "out_of_scope_en": [
    "accounting",
    "invoice / payment",
    "full ERP order management",
    "giant generic CRM",
    "broad Odoo entity mirroring",
    "source repo feature growth"
  ],
  "out_of_scope_ru": [
    "accounting",
    "invoice / payment",
    "full ERP order management",
    "giant generic CRM",
    "broad Odoo entity mirroring",
    "source repo feature growth"
  ],
  "active_context": {
    "updated_at": "`2026-04-17 04:35 +07`",
    "branch": "`develop`",
    "current_focus": "Fixed visual map generator fallback for standalone-owned capabilities and regenerated visual map docs",
    "last_verified_workflow_status": "PASS `./scripts/verify_workflow.sh`",
    "biggest_operational_risk": "no additional risk recorded"
  },
  "recent_worklog": [
    {
      "heading": "2026-04-17 04:35 +07 | develop",
      "summary": "Fixed visual map generator fallback for standalone-owned capabilities and regenerated visual map docs",
      "risk": "See worklog entry"
    },
    {
      "heading": "2026-04-17 04:33 +07 | develop",
      "summary": "Completed automatic root-doc sync for AGENTS.md and README.md",
      "risk": "See worklog entry"
    },
    {
      "heading": "2026-04-17 04:31 +07 | develop",
      "summary": "Made root operating docs truly auto-synced with project memory and automations",
      "risk": "See worklog entry"
    }
  ],
  "skills": [
    "audit-docs-vs-runtime",
    "ci-watch-fix",
    "docs-sync-curator",
    "donor-boundary-audit",
    "git-safe-commit",
    "operate-platform",
    "operate-standalone-intelligence",
    "project-visual-map",
    "release-readiness-gate",
    "skill-pattern-scan",
    "verify-implementation",
    "web-regression-pass"
  ],
  "automations": [
    "Hourly Repo Guard",
    "Hourly Platform Smoke",
    "Hourly Visual Map",
    "Weekly Release Gate"
  ]
}